MANIFEST.in
README.md
setup.cfg
setup.py
version.json
pythonflow/__init__.py
pythonflow/core.py
pythonflow/operations.py
pythonflow/util.py
pythonflow.egg-info/PKG-INFO
pythonflow.egg-info/SOURCES.txt
pythonflow.egg-info/dependency_links.txt
pythonflow.egg-info/top_level.txt
pythonflow/pfmq/__init__.py
pythonflow/pfmq/_base.py
pythonflow/pfmq/broker.py
pythonflow/pfmq/task.py
pythonflow/pfmq/worker.py