Metadata-Version: 2.1
Name: pythonflow
Version: 0.3.0
Summary: Dataflow programming for python
Home-page: https://github.com/spotify/pythonflow
Author: Till Hoffmann
Author-email: till@spotify.com
License: License :: OSI Approved :: Apache Software License
Platform: UNKNOWN
Classifier: Development Status :: 3 - Alpha
Classifier: Programming Language :: Python :: 3
Classifier: Topic :: Scientific/Engineering :: Artificial Intelligence
Classifier: Topic :: Utilities
Requires-Python: >=3
